certify_issuer/Issuer.py
certify_issuer/PdfIssuer.py
certify_issuer/__init__.py
certify_issuer/certify_sc_utils.py
certify_issuer/chainpoint.py
certify_issuer/pdf.py
certify_issuer/utils.py
test/__init__.py
test/test_issuer.py
certify_issuer-0.0.10.dist-info/LICENSE
certify_issuer-0.0.10.dist-info/METADATA
certify_issuer-0.0.10.dist-info/WHEEL
certify_issuer-0.0.10.dist-info/top_level.txt
certify_issuer-0.0.10.dist-info/RECORD
